MANIFEST.in
README.txt
requirements.txt
setup.py
webeditor/__init__.py
webeditor/config.py
webeditor/server.py
webeditor.egg-info/PKG-INFO
webeditor.egg-info/SOURCES.txt
webeditor.egg-info/dependency_links.txt
webeditor.egg-info/entry_points.txt
webeditor.egg-info/requires.txt
webeditor.egg-info/top_level.txt
webeditor/app/__init__.py
webeditor/app/attrdict.py
webeditor/app/exception.py
webeditor/app/handlers.py
webeditor/app/logger.py
webeditor/app/utils.py
webeditor/app/view_helper.py
webeditor/model/ErrNo.py
webeditor/model/__init__.py
webeditor/modules/__init__.py
webeditor/modules/web/__init__.py
webeditor/modules/web/apis.py
webeditor/modules/web/routing.py
webeditor/static/css/index.css
webeditor/static/css/query.css
webeditor/static/img/headimg.jpg
webeditor/static/libs/bootstrap-dynamic-tabs/bootstrap-dynamic-tabs.css
webeditor/static/libs/bootstrap-dynamic-tabs/bootstrap-dynamic-tabs.js
webeditor/static/node_modules/jquery/dist/core.js
webeditor/static/node_modules/jquery/dist/jquery.js
webeditor/static/node_modules/jquery/dist/jquery.min.js
webeditor/static/node_modules/jquery/dist/jquery.slim.js
webeditor/static/node_modules/jquery/dist/jquery.slim.min.js
webeditor/static/node_modules/jquery/external/sizzle/dist/sizzle.js
webeditor/static/node_modules/jquery/external/sizzle/dist/sizzle.min.js
webeditor/static/node_modules/jstree/dist/jstree.js
webeditor/static/node_modules/jstree/dist/jstree.min.js
webeditor/static/node_modules/jstree/dist/themes/default/32px.png
webeditor/static/node_modules/jstree/dist/themes/default/40px.png
webeditor/static/node_modules/jstree/dist/themes/default/style.css
webeditor/static/node_modules/jstree/dist/themes/default/style.min.css
webeditor/static/node_modules/jstree/dist/themes/default/throbber.gif
webeditor/static/node_modules/jstree/dist/themes/default-dark/32px.png
webeditor/static/node_modules/jstree/dist/themes/default-dark/40px.png
webeditor/static/node_modules/jstree/dist/themes/default-dark/style.css
webeditor/static/node_modules/jstree/dist/themes/default-dark/style.min.css
webeditor/static/node_modules/jstree/dist/themes/default-dark/throbber.gif
webeditor/static/node_modules/monaco-editor/min/vs/loader.js
