Metadata-Version: 1.0
Name: webeditor
Version: 0.5.0
Summary: Useful towel-related stuff.
Home-page: https://test.pypi.org/pypi/webeditor/
Author: shenli
Author-email: shenli1120@qq.com
License: LICENSE.txt
Platform: UNKNOWN
